treelstm/__init__.py
treelstm/tree_lstm.py
treelstm/util.py
pytorch_tree_lstm-0.1.3.dist-info/LICENSE
pytorch_tree_lstm-0.1.3.dist-info/METADATA
pytorch_tree_lstm-0.1.3.dist-info/WHEEL
pytorch_tree_lstm-0.1.3.dist-info/top_level.txt
pytorch_tree_lstm-0.1.3.dist-info/RECORD
