Metadata-Version: 2.1
Name: pytorch-tree-lstm
Version: 0.1.3
Summary: A Tree-LSTM model package for PyTorch
Home-page: https://github.com/unbounce/pytorch-tree-lstm
Author: Jordan Dawe
Author-email: jordan.dawe@unbounce.com
License: UNKNOWN
Platform: UNKNOWN
Classifier: Development Status :: 3 - Alpha
Classifier: Programming Language :: Python :: 3
Classifier: License :: OSI Approved :: MIT License
Classifier: Operating System :: OS Independent
Requires-Python: >=3
